setup.py
ankle/__init__.py
ankle/find.py
ankle/match.py
ankle/utils.py
ankle.egg-info/PKG-INFO
ankle.egg-info/SOURCES.txt
ankle.egg-info/dependency_links.txt
ankle.egg-info/requires.txt
ankle.egg-info/top_level.txt